{
  "name": "Velociraptor",
  "version": "0.2",
  "author": "Wes Lambert, @therealwlambert",
  "url": "https://github.com/TheHive-Project/Cortex-Analyzers",
  "license": "AGPL-V3",
  "description": "Run Velociraptor artifact collection",
  "dataTypeList": ["thehive:case_artifact"],
  "command": "Velociraptor/velociraptor_flow.py",
  "baseConfig": "Velociraptor",
  "configurationItems": [
    {
      "name": "velociraptor_client_config",
      "description": "Path to API client config file",
      "type": "string",
      "multi": false,
      "required": true,
      "defaultValue": ""
    },
    {
      "name": "velociraptor_artifact",
      "description": "Artifact to collect",
      "type": "string",
      "multi": false,
      "required": true,
      "defaultValue": ""
    },
    {
      "name": "query_max_duration",
      "description": "Max query duration (in seconds)",
      "type": "number",
      "multi": false,
      "required": false,
      "defaultValue": "600"
    }
  ]
}
